{"heartbeat": {"hora": "2026-06-03 00:07 UTC", "missatge": "Sistema operatiu. Sense alertes."}, "sistema": {"workflow": "sentinella", "freq": "cada 30 minuts (7h\u201317h, dill\u2013div)", "estat": "OK", "errors": "0", "actius_monitoritzats": 41}, "macro": {"tga": 0, "fed_balance": 0, "tipus_reals": 0}, "options_engine": {"vix": 0, "estocastic_spx": 0, "regim_macro": {"tga": 0, "fed_balance": 0, "tipus_reals": 0}}, "actius": [{"ticker": "BTC-EUR", "nom": "Bitcoin Spot", "capa": "Macro / Creixement", "preu": 57409.6, "variacio": 0.09, "hora": "2026-06-03 00:07 UTC", "semafor_macro": null, "fundamentals": null, "preus_7d": [57409.6]}, {"ticker": "ETH-EUR", "nom": "Ethereum Spot", "capa": "Macro / Creixement", "preu": 1602.58, "variacio": 0.28, "hora": "2026-06-03 00:07 UTC", "semafor_macro": null, "fundamentals": null, "preus_7d": [1602.58]}], "ultima_execucio": "2026-06-03 00:07 UTC"}
