{"heartbeat": {"hora": "2026-06-02 02:12 UTC", "missatge": "Sistema operatiu. Sense alertes."}, "sistema": {"workflow": "sentinella", "freq": "cada 30 minuts (7h\u201317h, dill\u2013div)", "estat": "OK", "errors": "0", "actius_monitoritzats": 41}, "macro": {"tga": 0, "fed_balance": 0, "tipus_reals": 0}, "options_engine": {"vix": 0, "estocastic_spx": 0, "regim_macro": {"tga": 0, "fed_balance": 0, "tipus_reals": 0}}, "actius": [{"ticker": "BTC-EUR", "nom": "Bitcoin Spot", "capa": "Macro / Creixement", "preu": 60318.13, "variacio": -1.59, "hora": "2026-06-02 02:12 UTC", "semafor_macro": null, "fundamentals": null, "preus_7d": [60318.13]}, {"ticker": "ETH-EUR", "nom": "Ethereum Spot", "capa": "Macro / Creixement", "preu": 1688.92, "variacio": -1.93, "hora": "2026-06-02 02:12 UTC", "semafor_macro": null, "fundamentals": null, "preus_7d": [1688.92]}], "ultima_execucio": "2026-06-02 02:12 UTC"}
